netspresso/VERSION
netspresso/__init__.py
netspresso/analytics.py
netspresso/base.py
netspresso/netspresso.py
netspresso/clients/__init__.py
netspresso/clients/config.py
netspresso/clients/auth/__init__.py
netspresso/clients/auth/client.py
netspresso/clients/auth/request_body.py
netspresso/clients/auth/response_body.py
netspresso/clients/auth/v2/__init__.py
netspresso/clients/auth/v2/client.py
netspresso/clients/auth/v2/schemas/__init__.py
netspresso/clients/auth/v2/schemas/auth.py
netspresso/clients/auth/v2/schemas/common.py
netspresso/clients/auth/v2/schemas/credit.py
netspresso/clients/auth/v2/schemas/token.py
netspresso/clients/auth/v2/schemas/user.py
netspresso/clients/auth/v2/schemas/user_agreement.py
netspresso/clients/compressor/__init__.py
netspresso/clients/compressor/v2/__init__.py
netspresso/clients/compressor/v2/main.py
netspresso/clients/compressor/v2/schemas/__init__.py
netspresso/clients/compressor/v2/schemas/common.py
netspresso/clients/compressor/v2/schemas/compression/__init__.py
netspresso/clients/compressor/v2/schemas/compression/base.py
netspresso/clients/compressor/v2/schemas/compression/request_body.py
netspresso/clients/compressor/v2/schemas/compression/response_body.py
netspresso/clients/compressor/v2/schemas/model/__init__.py
netspresso/clients/compressor/v2/schemas/model/base.py
netspresso/clients/compressor/v2/schemas/model/request_body.py
netspresso/clients/compressor/v2/schemas/model/response_body.py
netspresso/clients/configs/config-v2-prod-cloud.ini
netspresso/clients/launcher/__init__.py
netspresso/clients/launcher/v2/__init__.py
netspresso/clients/launcher/v2/benchmarker.py
netspresso/clients/launcher/v2/converter.py
netspresso/clients/launcher/v2/graph_optimizer.py
netspresso/clients/launcher/v2/main.py
netspresso/clients/launcher/v2/quantizer.py
netspresso/clients/launcher/v2/simulator.py
netspresso/clients/launcher/v2/utils.py
netspresso/clients/launcher/v2/implements/__init__.py
netspresso-1.16.1.dist-info/LICENSE
netspresso-1.16.1.dist-info/METADATA
netspresso-1.16.1.dist-info/WHEEL
netspresso-1.16.1.dist-info/top_level.txt
netspresso-1.16.1.dist-info/RECORD
