Metadata-Version: 2.1
Name: netspresso
Version: 1.16.1
Summary: PyNetsPresso
Home-page: https://github.com/Nota-NetsPresso/PyNetsPresso
Author: NetsPresso
Author-email: netspresso@nota.ai
License: UNKNOWN
Platform: UNKNOWN
Classifier: Intended Audience :: Developers
Classifier: Intended Audience :: Science/Research
Classifier: Operating System :: OS Independent
Classifier: Programming Language :: Python :: 3.8
Classifier: Programming Language :: Python :: 3.9
Classifier: Programming Language :: Python :: 3.10
Classifier: Topic :: Scientific/Engineering :: Artificial Intelligence
Requires-Python: >=3.8
Requires-Dist: urllib3
Requires-Dist: requests
Requires-Dist: loguru>=0.7.0
Requires-Dist: PyJWT>=2.7.0
Requires-Dist: email-validator>=2.0.0
Requires-Dist: pytz>=2023.3
Requires-Dist: netspresso-trainer==1.3.1
Requires-Dist: PyGithub>=2.1.1
Requires-Dist: matplotlib>=3.7.4
Requires-Dist: aenum>=3.1.15
Requires-Dist: requests-toolbelt>=1.0.0
Requires-Dist: python-dotenv>=1.0.0
Requires-Dist: netspresso-inference-package==0.1.4
Requires-Dist: scipy
Requires-Dist: qai-hub==0.29.0
